br_ping_gui/__init__.py
br_ping_gui/seportgui.py
br_ping_gui-0.0.3.dist-info/METADATA
br_ping_gui-0.0.3.dist-info/WHEEL
br_ping_gui-0.0.3.dist-info/entry_points.txt
br_ping_gui-0.0.3.dist-info/top_level.txt
br_ping_gui-0.0.3.dist-info/RECORD
