Metadata-Version: 2.1
Name: br-ping-gui
Version: 0.0.3
Summary: A python library for viewing and recording a bluerobotics ping 2 sensor..
Author-email: Javier Alonso <jalfe@dtu.dk>, Fletcher Thompson <fletho@aqua.dtu.dk>
Project-URL: Homepage, https://gitlab.gbar.dtu.dk/dtu-aqua-observation-technology/sonar/br_ping_gui
Project-URL: Issues, https://gitlab.gbar.dtu.dk/dtu-aqua-observation-technology/sonar/br_ping_gui/-/issues
Classifier: Programming Language :: Python :: 3
Classifier: License :: OSI Approved :: Apache Software License
Classifier: Operating System :: OS Independent
Requires-Python: >=3.10
Requires-Dist: bluerobotics-ping
Requires-Dist: numpy
Requires-Dist: matplotlib
Requires-Dist: customtkinter
